333/__init__.py
code_repository/1.py
code_repository/2.py
code_repository/AliasMethod.py
code_repository/Dense Optical Flow in OpenCV.py
code_repository/Mydistr.py
code_repository/RGBNorm.py
code_repository/SegmenationMetric.py
code_repository/__init__.py
code_repository/adjust_lr.py
code_repository/autograd.py
code_repository/autograd_Function.py
code_repository/autograd_profiler.py
code_repository/calculate_md5.py
code_repository/iter.py
code_repository/knn_prediction.py
code_repository/topk_accuracy.py
blueee-1.1.4.dist-info/METADATA
blueee-1.1.4.dist-info/WHEEL
blueee-1.1.4.dist-info/top_level.txt
blueee-1.1.4.dist-info/RECORD
